COPYING
MANIFEST.in
README.md
doc.md
setup.py
src/radispawn/__init__.py
src/radispawn/__main__.py
src/radispawn.egg-info/PKG-INFO
src/radispawn.egg-info/SOURCES.txt
src/radispawn.egg-info/dependency_links.txt
src/radispawn.egg-info/entry_points.txt
src/radispawn.egg-info/requires.txt
src/radispawn.egg-info/top_level.txt
src/radispawn/radial_widget/__init__.py
src/radispawn/radial_widget/radial_widget.py